{"bff_meta":null,"error":null,"error_msg":null,"data":{"shopid":100278520,"userid":100279999,"last_active_time":1698670963,"vacation":false,"place":"KOTA BANDUNG - BOJONGLOA KIDUL, JAWA BARAT, ID","account":{"portrait":"8fd5301299d4d6be99ae90e2b4f853db","username":"hegarabadijaya","status":1},"is_shopee_verified":true,"is_preferred_plus_seller":true,"is_official_shop":false,"shop_location":"KOTA BANDUNG","item_count":1090,"rating_star":4.857991,"response_rate":100,"session_info":null,"name":"hegarabadijaya","ctime":1540982388,"response_time":513,"follower_count":59876,"show_official_shop_label":false,"rating_bad":1202,"rating_good":204751,"rating_normal":3775,"session_infos":null,"show_shopee_mission":false,"status":1,"is_individual_seller":null,"is_3pf":false}}