{"bff_meta":null,"error":null,"error_msg":null,"data":{"shopid":101258889,"userid":101260368,"last_active_time":1698639012,"vacation":false,"place":"KAB. CIREBON - DEPOK, JAWA BARAT, ID","account":{"portrait":"4706631bb765749a4125483b9ac86dd9","username":"diah_didi.gift","status":1},"is_shopee_verified":true,"is_preferred_plus_seller":true,"is_official_shop":false,"shop_location":"KAB. CIREBON","item_count":38,"rating_star":4.74523,"response_rate":51,"session_info":null,"name":"kharisrachmadyzet","ctime":1541306868,"response_time":13151,"follower_count":2357,"show_official_shop_label":false,"rating_bad":16,"rating_good":2788,"rating_normal":122,"session_infos":null,"show_shopee_mission":false,"status":1,"is_individual_seller":null,"is_3pf":false}}