{"bff_meta":null,"error":null,"error_msg":null,"data":{"shopid":105944383,"userid":105945862,"last_active_time":1698654688,"vacation":false,"place":"KOTA JAKARTA TIMUR - KRAMAT JATI, DKI JAKARTA, ID","account":{"portrait":"61b5575162938440d5129d5f47b7804f","username":"gudangmurah23","status":1},"is_shopee_verified":false,"is_preferred_plus_seller":false,"is_official_shop":false,"shop_location":"KOTA JAKARTA TIMUR","item_count":668,"rating_star":4.823916,"response_rate":72,"session_info":null,"name":"gudangmurah23","ctime":1542589421,"response_time":7603,"follower_count":2830,"show_official_shop_label":false,"rating_bad":57,"rating_good":9367,"rating_normal":236,"session_infos":null,"show_shopee_mission":false,"status":1,"is_individual_seller":null,"is_3pf":false}}