{"bff_meta":null,"error":null,"error_msg":null,"data":{"shopid":106780695,"userid":106782174,"last_active_time":1698672145,"vacation":false,"place":"KOTA BANDUNG - KIARACONDONG, JAWA BARAT, ID","account":{"portrait":"a33afd015f2f85a45e82ae2698b65356","username":"voidstune","status":1},"is_shopee_verified":true,"is_preferred_plus_seller":true,"is_official_shop":false,"shop_location":"KOTA BANDUNG","item_count":4353,"rating_star":4.806299,"response_rate":90,"session_info":null,"name":"Fortunato","ctime":1542799923,"response_time":5972,"follower_count":5210,"show_official_shop_label":false,"rating_bad":203,"rating_good":28425,"rating_normal":864,"session_infos":null,"show_shopee_mission":false,"status":1,"is_individual_seller":null,"is_3pf":false}}