{"bff_meta":null,"error":null,"error_msg":null,"data":{"shopid":106892939,"userid":106894418,"last_active_time":1698668489,"vacation":false,"place":"KOTA SURAKARTA (SOLO) - BANJARSARI, JAWA TENGAH, ID","account":{"portrait":"1018052f73073a6e94b7a0591c4c9e7b","username":"micmax_indonesia","status":1},"is_shopee_verified":true,"is_preferred_plus_seller":true,"is_official_shop":false,"shop_location":"KOTA SURAKARTA (SOLO)","item_count":85,"rating_star":4.804302,"response_rate":96,"session_info":null,"name":"Sehat Probiotik","ctime":1542852727,"response_time":8766,"follower_count":6229,"show_official_shop_label":false,"rating_bad":52,"rating_good":9614,"rating_normal":227,"session_infos":null,"show_shopee_mission":false,"status":1,"is_individual_seller":null,"is_3pf":false}}