{"bff_meta":null,"error":null,"error_msg":null,"data":{"shopid":10712984,"userid":10714282,"last_active_time":1698669302,"vacation":false,"place":"KOTA DEPOK - SUKMAJAYA, JAWA BARAT, ID","account":{"portrait":"8a88ca66b265d98e66af07320e506688","username":"pusatkaoskaki_muslimah","status":1},"is_shopee_verified":true,"is_preferred_plus_seller":true,"is_official_shop":false,"shop_location":"KOTA DEPOK","item_count":223,"rating_star":4.904716,"response_rate":93,"session_info":null,"name":"pusatkaoskaki_muslimah","ctime":1475726617,"response_time":6978,"follower_count":30503,"show_official_shop_label":false,"rating_bad":17,"rating_good":19811,"rating_normal":163,"session_infos":null,"show_shopee_mission":false,"status":1,"is_individual_seller":null,"is_3pf":false}}