{"bff_meta":null,"error":null,"error_msg":null,"data":{"shopid":112626432,"userid":112628030,"last_active_time":1698672272,"vacation":false,"place":"KAB. TANGERANG - KOSAMBI, BANTEN, ID","account":{"portrait":"9db8874d100907bdb089a7eafb2bc9f1","username":"shopaholic.official","status":1},"is_shopee_verified":true,"is_preferred_plus_seller":true,"is_official_shop":false,"shop_location":"KAB. TANGERANG","item_count":151,"rating_star":4.701053,"response_rate":97,"session_info":null,"name":"Shopaholic Official","ctime":1544458049,"response_time":7508,"follower_count":127221,"show_official_shop_label":false,"rating_bad":4466,"rating_good":221860,"rating_normal":11143,"session_infos":null,"show_shopee_mission":false,"status":1,"is_individual_seller":null,"is_3pf":false}}