{"bff_meta":null,"error":null,"error_msg":null,"data":{"shopid":11966977,"userid":11968279,"last_active_time":1698670865,"vacation":false,"place":"KOTA TANGERANG SELATAN - PAMULANG, BANTEN, ID","account":{"portrait":"b8de16c0ac0da10ab31abf419d313026","username":"sandisy","status":1},"is_shopee_verified":false,"is_preferred_plus_seller":false,"is_official_shop":false,"shop_location":"KOTA TANGERANG SELATAN","item_count":81,"rating_star":4.929931,"response_rate":94,"session_info":null,"name":"sandisy cake","ctime":1478383846,"response_time":7574,"follower_count":2509,"show_official_shop_label":false,"rating_bad":3,"rating_good":1307,"rating_normal":8,"session_infos":null,"show_shopee_mission":false,"status":1,"is_individual_seller":null,"is_3pf":false}}