{"bff_meta":null,"error":null,"error_msg":null,"data":{"shopid":134605647,"userid":134607471,"last_active_time":1698653611,"vacation":false,"place":"KAB. BANYUWANGI - GAMBIRAN, JAWA TIMUR, ID","account":{"portrait":"c5a7e105f6f03a47e72b4248620cfc7f","username":"dbeja_bwi","status":1},"is_shopee_verified":false,"is_preferred_plus_seller":false,"is_official_shop":false,"shop_location":"KAB. BANYUWANGI","item_count":11,"rating_star":4.9,"response_rate":47,"session_info":null,"name":"Dbeja_Bwi","ctime":1553075548,"response_time":13261,"follower_count":110,"show_official_shop_label":false,"rating_bad":0,"rating_good":50,"rating_normal":1,"session_infos":null,"show_shopee_mission":false,"status":1,"is_individual_seller":null,"is_3pf":false}}