{"bff_meta":null,"error":null,"error_msg":null,"data":{"shopid":14260675,"userid":14261979,"last_active_time":1698667374,"vacation":false,"place":"KOTA JAKARTA PUSAT - JOHAR BARU, DKI JAKARTA, ID","account":{"portrait":"8abb4f8656d6afc8b1200867074574e2","username":"auliajaya04","status":1},"is_shopee_verified":true,"is_preferred_plus_seller":true,"is_official_shop":false,"shop_location":"KOTA JAKARTA PUSAT","item_count":266,"rating_star":4.80625,"response_rate":97,"session_info":null,"name":"Aulia Jaya","ctime":1482668519,"response_time":1283,"follower_count":2919,"show_official_shop_label":false,"rating_bad":27,"rating_good":5199,"rating_normal":141,"session_infos":null,"show_shopee_mission":false,"status":1,"is_individual_seller":null,"is_3pf":false}}