{"bff_meta":null,"error":null,"error_msg":null,"data":{"shopid":15089841,"userid":15091177,"last_active_time":1698670565,"vacation":false,"place":"KOTA BANDUNG - ANDIR, JAWA BARAT, ID","account":{"portrait":"2c9f2376f27ec5600b67d7053efab3e7","username":"spadeanime","status":1},"is_shopee_verified":true,"is_preferred_plus_seller":false,"is_official_shop":false,"shop_location":"KOTA BANDUNG","item_count":276,"rating_star":4.695859,"response_rate":92,"session_info":null,"name":"Spadeanime","ctime":1484276447,"response_time":8480,"follower_count":3931,"show_official_shop_label":false,"rating_bad":62,"rating_good":5737,"rating_normal":342,"session_infos":null,"show_shopee_mission":false,"status":1,"is_individual_seller":null,"is_3pf":false}}