{"bff_meta":null,"error":null,"error_msg":null,"data":{"shopid":15545069,"userid":15546405,"last_active_time":1698668775,"vacation":false,"place":"KAB. BANDUNG - MARGAHAYU, JAWA BARAT, ID","account":{"portrait":"f2921d401355678de5c0bf62a168fc35","username":"kamuflase_os_86","status":1},"is_shopee_verified":true,"is_preferred_plus_seller":true,"is_official_shop":false,"shop_location":"KAB. BANDUNG","item_count":341,"rating_star":4.688011,"response_rate":92,"session_info":null,"name":"KAMUFLASE OS 86","ctime":1485106717,"response_time":4323,"follower_count":18930,"show_official_shop_label":false,"rating_bad":377,"rating_good":29210,"rating_normal":1627,"session_infos":null,"show_shopee_mission":false,"status":1,"is_individual_seller":null,"is_3pf":false}}