{"bff_meta":null,"error":null,"error_msg":null,"data":{"shopid":162294125,"userid":162296249,"last_active_time":1698669570,"vacation":false,"place":"KOTA JAKARTA PUSAT - KEMAYORAN, DKI JAKARTA, ID","account":{"portrait":"3eaabc149905991ad2a2dad5d01c21a0","username":"angeliefashion","status":1},"is_shopee_verified":true,"is_preferred_plus_seller":true,"is_official_shop":false,"shop_location":"KOTA JAKARTA PUSAT","item_count":100,"rating_star":4.687185,"response_rate":99,"session_info":null,"name":"AngelieFashion","ctime":1562927852,"response_time":1575,"follower_count":3458,"show_official_shop_label":false,"rating_bad":325,"rating_good":32194,"rating_normal":1754,"session_infos":null,"show_shopee_mission":false,"status":1,"is_individual_seller":null,"is_3pf":false}}