{"bff_meta":null,"error":null,"error_msg":null,"data":{"shopid":167065264,"userid":167067530,"last_active_time":1698669533,"vacation":false,"place":"KOTA TANGERANG - BATUCEPER, BANTEN, ID","account":{"portrait":"fc51e01d61ea93844fc2bb934870b2ea","username":"de_ombrello","status":1},"is_shopee_verified":true,"is_preferred_plus_seller":true,"is_official_shop":false,"shop_location":"KOTA TANGERANG","item_count":208,"rating_star":4.819372,"response_rate":93,"session_info":null,"name":"De'Ombrello","ctime":1564632789,"response_time":3909,"follower_count":8147,"show_official_shop_label":false,"rating_bad":362,"rating_good":54483,"rating_normal":1444,"session_infos":null,"show_shopee_mission":false,"status":1,"is_individual_seller":null,"is_3pf":false}}