{"bff_meta":null,"error":null,"error_msg":null,"data":{"shopid":16879370,"userid":16880706,"last_active_time":1698668473,"vacation":false,"place":"KOTA BANDUNG - SUKAJADI, JAWA BARAT, ID","account":{"portrait":"5a8ab40ed781c6949260a329e1354697","username":"sevenstereo","status":1},"is_shopee_verified":true,"is_preferred_plus_seller":true,"is_official_shop":false,"shop_location":"KOTA BANDUNG","item_count":4664,"rating_star":4.875277,"response_rate":97,"session_info":null,"name":"Seven Stereo Music \u0026 Audio Store","ctime":1487586619,"response_time":3884,"follower_count":22938,"show_official_shop_label":false,"rating_bad":92,"rating_good":16862,"rating_normal":291,"session_infos":null,"show_shopee_mission":false,"status":1,"is_individual_seller":null,"is_3pf":false}}