{"bff_meta":null,"error":null,"error_msg":null,"data":{"shopid":18069251,"userid":18070587,"last_active_time":1698670922,"vacation":false,"place":"KAB. SLEMAN - MLATI, DI YOGYAKARTA, ID","account":{"portrait":"47fcb0a39c173c5588755c9ef36a143f","username":"bunglonbabyshop","status":1},"is_shopee_verified":true,"is_preferred_plus_seller":true,"is_official_shop":false,"shop_location":"KAB. SLEMAN","item_count":912,"rating_star":4.827437,"response_rate":97,"session_info":null,"name":"Bunglon Babyshop","ctime":1489329802,"response_time":2800,"follower_count":13636,"show_official_shop_label":false,"rating_bad":77,"rating_good":27730,"rating_normal":662,"session_infos":null,"show_shopee_mission":false,"status":1,"is_individual_seller":null,"is_3pf":false}}