{"bff_meta":null,"error":null,"error_msg":null,"data":{"shopid":19175871,"userid":19177207,"last_active_time":1698671588,"vacation":false,"place":"KAB. TANGERANG - CIKUPA, BANTEN, ID","account":{"portrait":"f1dc63e7c0129703856077d6f7c6864c","username":"chandra_phone_store","status":1},"is_shopee_verified":true,"is_preferred_plus_seller":true,"is_official_shop":false,"shop_location":"KAB. TANGERANG","item_count":458,"rating_star":4.778201,"response_rate":92,"session_info":null,"name":"KOIN acc","ctime":1490736154,"response_time":10075,"follower_count":16021,"show_official_shop_label":false,"rating_bad":392,"rating_good":35806,"rating_normal":1346,"session_infos":null,"show_shopee_mission":false,"status":1,"is_individual_seller":null,"is_3pf":false}}