{"bff_meta":null,"error":null,"error_msg":null,"data":{"shopid":22665286,"userid":22666622,"last_active_time":1698670520,"vacation":false,"place":"KOTA JAKARTA BARAT - TAMAN SARI, DKI JAKARTA, ID","account":{"portrait":"3ce530f9859872dd8c0c831702a1f6b8","username":"klop_store","status":1},"is_shopee_verified":true,"is_preferred_plus_seller":true,"is_official_shop":false,"shop_location":"KOTA JAKARTA BARAT","item_count":162,"rating_star":4.79929,"response_rate":99,"session_info":null,"name":"KLOP STORE","ctime":1495009311,"response_time":3353,"follower_count":618,"show_official_shop_label":false,"rating_bad":76,"rating_good":7088,"rating_normal":188,"session_infos":null,"show_shopee_mission":false,"status":1,"is_individual_seller":null,"is_3pf":false}}