{"bff_meta":null,"error":null,"error_msg":null,"data":{"shopid":230467967,"userid":230472610,"last_active_time":1698666845,"vacation":false,"place":"KAB. BANDUNG BARAT - CILILIN, JAWA BARAT, ID","account":{"portrait":"ce26d44e09e0e3b35c0b0f9ef928c7c5","username":"alpi12_12","status":1},"is_shopee_verified":true,"is_preferred_plus_seller":true,"is_official_shop":false,"shop_location":"KAB. BANDUNG BARAT","item_count":177,"rating_star":4.778868,"response_rate":99,"session_info":null,"name":"danesta olshop","ctime":1582544618,"response_time":3285,"follower_count":271,"show_official_shop_label":false,"rating_bad":9,"rating_good":1316,"rating_normal":37,"session_infos":null,"show_shopee_mission":false,"status":1,"is_individual_seller":null,"is_3pf":false}}