{"bff_meta":null,"error":null,"error_msg":null,"data":{"shopid":23696826,"userid":23698162,"last_active_time":1698671340,"vacation":false,"place":"KAB. KEDIRI - RINGINREJO, JAWA TIMUR, ID","account":{"portrait":"8a3237bc1fe77affb24c25e067f58392","username":"idhaneyfa","status":1},"is_shopee_verified":true,"is_preferred_plus_seller":false,"is_official_shop":false,"shop_location":"KAB. KEDIRI","item_count":190,"rating_star":4.867396,"response_rate":90,"session_info":{"is_show":true,"session_id":45251631,"view_count":8,"session_url":"https://play-tx-src.livestream.shopee.co.id/live/id-live-198566-45251631.flv?auditkey=1.0~27L5QDqwYdCHFelK7Hx9QYrQvHV94CVhTjecm0cihN4cx2rgDyDJbCvT8Y71IrACj6jxGO3yphcf-j5bvg4QlZI-RAllPNc960dHUaCw-E8~42815816884b19d7690939e0792d578223ff637dcde7cdb05b436924f809350b\u0026cdnID=TXCLOUD\u0026expire_ts=1698673250","preview_image":"id-11134104-7r98q-lngm488bzs06a9"},"name":"idhaneyfa","ctime":1496029348,"response_time":8518,"follower_count":16443,"show_official_shop_label":false,"rating_bad":50,"rating_good":18539,"rating_normal":296,"session_infos":[{"is_show":true,"session_id":45251631,"view_count":8,"session_url":"https://play-tx-src.livestream.shopee.co.id/live/id-live-198566-45251631.flv?auditkey=1.0~27L5QDqwYdCHFelK7Hx9QYrQvHV94CVhTjecm0cihN4cx2rgDyDJbCvT8Y71IrACj6jxGO3yphcf-j5bvg4QlZI-RAllPNc960dHUaCw-E8~42815816884b19d7690939e0792d578223ff637dcde7cdb05b436924f809350b\u0026cdnID=TXCLOUD\u0026expire_ts=1698673250","preview_image":"id-11134104-7r98q-lngm488bzs06a9"}],"show_shopee_mission":false,"status":1,"is_individual_seller":null,"is_3pf":false}}