{"bff_meta":null,"error":null,"error_msg":null,"data":{"shopid":241411089,"userid":241416645,"last_active_time":1698657626,"vacation":false,"place":"KOTA SURABAYA - MULYOREJO, JAWA TIMUR, ID","account":{"portrait":"4113ce0c8c6a0082de8f22a160fcb576","username":"juarasilatstore","status":1},"is_shopee_verified":true,"is_preferred_plus_seller":true,"is_official_shop":false,"shop_location":"KOTA SURABAYA","item_count":308,"rating_star":4.769393,"response_rate":89,"session_info":null,"name":"Juara Silat Store","ctime":1585911762,"response_time":15915,"follower_count":17863,"show_official_shop_label":false,"rating_bad":405,"rating_good":45695,"rating_normal":1606,"session_infos":null,"show_shopee_mission":false,"status":1,"is_individual_seller":null,"is_3pf":false}}