{"bff_meta":null,"error":null,"error_msg":null,"data":{"shopid":242697883,"userid":242703512,"last_active_time":1698672107,"vacation":false,"place":"KOTA CIREBON - LEMAHWUNGKUK, JAWA BARAT, ID","account":{"portrait":"86c9e0863b121393e83ff8fce5d649ba","username":"kanno_textile","status":1},"is_shopee_verified":true,"is_preferred_plus_seller":true,"is_official_shop":false,"shop_location":"KOTA CIREBON","item_count":359,"rating_star":4.8545,"response_rate":90,"session_info":null,"name":"Kanno Textile","ctime":1586268362,"response_time":5839,"follower_count":11410,"show_official_shop_label":false,"rating_bad":54,"rating_good":9017,"rating_normal":172,"session_infos":null,"show_shopee_mission":false,"status":1,"is_individual_seller":null,"is_3pf":false}}