{"bff_meta":null,"error":null,"error_msg":null,"data":{"shopid":2473676,"userid":2474955,"last_active_time":1698671239,"vacation":false,"place":"KAB. BOGOR - CIBINONG, JAWA BARAT, ID","account":{"portrait":"8e4a0e5965f9df2a41ba5feb9afc9d11","username":"angga.maulana","status":1},"is_shopee_verified":true,"is_preferred_plus_seller":true,"is_official_shop":false,"shop_location":"KAB. BOGOR","item_count":2550,"rating_star":4.769221,"response_rate":95,"session_info":null,"name":"Djasmine Acc \u0026 Spare Part HP","ctime":1451206509,"response_time":5925,"follower_count":4362,"show_official_shop_label":false,"rating_bad":230,"rating_good":15889,"rating_normal":567,"session_infos":null,"show_shopee_mission":false,"status":1,"is_individual_seller":null,"is_3pf":false}}