{"bff_meta":null,"error":null,"error_msg":null,"data":{"shopid":252050609,"userid":252051131,"last_active_time":1698667099,"vacation":false,"place":"KOTA JAKARTA UTARA - PENJARINGAN, DKI JAKARTA, ID","account":{"portrait":"9582198bc54bdf3c7f73ef51c5250c82","username":"mollinicshoes","status":1},"is_shopee_verified":false,"is_preferred_plus_seller":false,"is_official_shop":true,"shop_location":"KOTA JAKARTA UTARA","item_count":134,"rating_star":4.857208,"response_rate":74,"session_info":null,"name":"Mollinic Official Shop","ctime":1587368875,"response_time":9977,"follower_count":28999,"show_official_shop_label":true,"rating_bad":34,"rating_good":10904,"rating_normal":178,"session_infos":null,"show_shopee_mission":false,"status":1,"is_individual_seller":null,"is_3pf":false}}