{"bff_meta":null,"error":null,"error_msg":null,"data":{"shopid":255024673,"userid":255025540,"last_active_time":1698671122,"vacation":false,"place":"KOTA SURABAYA - TEGALSARI, JAWA TIMUR, ID","account":{"portrait":"b31f77210bc2fff6476cfc65ba1a80bd","username":"vivacosmetics.surabaya","status":1},"is_shopee_verified":false,"is_preferred_plus_seller":false,"is_official_shop":true,"shop_location":"KOTA SURABAYA","item_count":286,"rating_star":4.892294,"response_rate":100,"session_info":null,"name":"Viva Cosmetics Authorized Store Surabaya","ctime":1588062364,"response_time":3851,"follower_count":513900,"show_official_shop_label":true,"rating_bad":1201,"rating_good":772514,"rating_normal":8576,"session_infos":null,"show_shopee_mission":false,"status":1,"is_individual_seller":null,"is_3pf":false}}