{"bff_meta":null,"error":null,"error_msg":null,"data":{"shopid":266538090,"userid":266540937,"last_active_time":1698639804,"vacation":false,"place":"KOTA MALANG - SUKUN, JAWA TIMUR, ID","account":{"portrait":"7bbfcfa17725da0e3380533179be168b","username":"aquayas","status":1},"is_shopee_verified":false,"is_preferred_plus_seller":false,"is_official_shop":false,"shop_location":"KOTA MALANG","item_count":219,"rating_star":4.858214,"response_rate":38,"session_info":null,"name":"aquayas","ctime":1590429554,"response_time":7942,"follower_count":4173,"show_official_shop_label":false,"rating_bad":54,"rating_good":7723,"rating_normal":133,"session_infos":null,"show_shopee_mission":false,"status":1,"is_individual_seller":null,"is_3pf":false}}