{"bff_meta":null,"error":null,"error_msg":null,"data":{"shopid":267489492,"userid":267492734,"last_active_time":1698669576,"vacation":false,"place":"KOTA MAKASSAR - MAKASSAR, SULAWESI SELATAN, ID","account":{"portrait":"3a17097a502a2fe9fe42bc5cbae9193c","username":"daniel32jo","status":1},"is_shopee_verified":false,"is_preferred_plus_seller":false,"is_official_shop":false,"shop_location":"KOTA MAKASSAR","item_count":2377,"rating_star":4.864391,"response_rate":21,"session_info":null,"name":"MAKASSAR ATK - ATEKA MART","ctime":1590637081,"response_time":15307,"follower_count":17798,"show_official_shop_label":false,"rating_bad":470,"rating_good":97684,"rating_normal":1624,"session_infos":null,"show_shopee_mission":false,"status":1,"is_individual_seller":null,"is_3pf":false}}