{"bff_meta":null,"error":null,"error_msg":null,"data":{"shopid":2916918,"userid":2918292,"last_active_time":1698668070,"vacation":false,"place":"KOTA BALIKPAPAN - BALIKPAPAN TENGAH, KALIMANTAN TIMUR, ID","account":{"portrait":"4a6bd821f0b7003194b2c009d0525729","username":"hi_photo","status":1},"is_shopee_verified":true,"is_preferred_plus_seller":false,"is_official_shop":false,"shop_location":"KOTA BALIKPAPAN","item_count":17,"rating_star":4.929448,"response_rate":43,"session_info":null,"name":"HI Photo Camera ","ctime":1453526583,"response_time":7976,"follower_count":505,"show_official_shop_label":false,"rating_bad":1,"rating_good":331,"rating_normal":1,"session_infos":null,"show_shopee_mission":false,"status":1,"is_individual_seller":null,"is_3pf":false}}