{"bff_meta":null,"error":null,"error_msg":null,"data":{"shopid":293022711,"userid":293042012,"last_active_time":1698662153,"vacation":false,"place":"KAB. PONOROGO - PONOROGO, JAWA TIMUR, ID","account":{"portrait":"da890439d3c387b3ff4b40b8b02d7663","username":"vb.store89","status":1},"is_shopee_verified":true,"is_preferred_plus_seller":true,"is_official_shop":false,"shop_location":"KAB. PONOROGO","item_count":483,"rating_star":4.84276,"response_rate":100,"session_info":null,"name":"vb.store89","ctime":1596636757,"response_time":10239,"follower_count":36631,"show_official_shop_label":false,"rating_bad":225,"rating_good":72267,"rating_normal":1597,"session_infos":null,"show_shopee_mission":false,"status":1,"is_individual_seller":null,"is_3pf":false}}