{"bff_meta":null,"error":null,"error_msg":null,"data":{"shopid":313087081,"userid":313106680,"last_active_time":1698658626,"vacation":false,"place":"KOTA JAKARTA TIMUR - PASAR REBO, DKI JAKARTA, ID","account":{"portrait":"95a979c326256659cd96d5bb700e1488","username":"matapshopgrosir69","status":1},"is_shopee_verified":true,"is_preferred_plus_seller":true,"is_official_shop":false,"shop_location":"KOTA JAKARTA TIMUR","item_count":259,"rating_star":4.735255,"response_rate":73,"session_info":null,"name":"Mantap shop 69++","ctime":1600770680,"response_time":11975,"follower_count":1249,"show_official_shop_label":false,"rating_bad":266,"rating_good":18217,"rating_normal":821,"session_infos":null,"show_shopee_mission":false,"status":1,"is_individual_seller":null,"is_3pf":false}}