{"bff_meta":null,"error":null,"error_msg":null,"data":{"shopid":325002719,"userid":325022318,"last_active_time":1698671318,"vacation":false,"place":"KAB. TANGERANG - KELAPA DUA, BANTEN, ID","account":{"portrait":"8219ae3a2d0fe1106cfcecc636fe4ab0","username":"superfeel_official","status":1},"is_shopee_verified":true,"is_preferred_plus_seller":true,"is_official_shop":false,"shop_location":"KAB. TANGERANG","item_count":399,"rating_star":4.743855,"response_rate":84,"session_info":null,"name":"Superfeel Official","ctime":1603119598,"response_time":7763,"follower_count":30737,"show_official_shop_label":false,"rating_bad":886,"rating_good":102581,"rating_normal":4727,"session_infos":null,"show_shopee_mission":false,"status":1,"is_individual_seller":null,"is_3pf":false}}