{"bff_meta":null,"error":null,"error_msg":null,"data":{"shopid":32670108,"userid":32671492,"last_active_time":1698669039,"vacation":false,"place":"KOTA MAKASSAR - TALLO, SULAWESI SELATAN, ID","account":{"portrait":"0b01c152c1a547c00ca6529272b99402","username":"herbalam","status":1},"is_shopee_verified":true,"is_preferred_plus_seller":false,"is_official_shop":false,"shop_location":"KOTA MAKASSAR","item_count":6,"rating_star":4.788745,"response_rate":98,"session_info":null,"name":"HERBALAM","ctime":1504131657,"response_time":1868,"follower_count":2923,"show_official_shop_label":false,"rating_bad":76,"rating_good":12812,"rating_normal":360,"session_infos":null,"show_shopee_mission":false,"status":1,"is_individual_seller":null,"is_3pf":false}}