{"bff_meta":null,"error":null,"error_msg":null,"data":{"shopid":331777884,"userid":331797459,"last_active_time":1698662308,"vacation":false,"place":"KOTA JAKARTA BARAT - TAMBORA, DKI JAKARTA, ID","account":{"portrait":"2673c06f57fab7b610e669a2a820af98","username":"torreto.id99","status":1},"is_shopee_verified":true,"is_preferred_plus_seller":true,"is_official_shop":false,"shop_location":"KOTA JAKARTA BARAT","item_count":89,"rating_star":4.505481,"response_rate":84,"session_info":null,"name":"TORETTO","ctime":1604388534,"response_time":7814,"follower_count":14753,"show_official_shop_label":false,"rating_bad":1807,"rating_good":62044,"rating_normal":6669,"session_infos":null,"show_shopee_mission":false,"status":1,"is_individual_seller":null,"is_3pf":false}}