{"bff_meta":null,"error":null,"error_msg":null,"data":{"shopid":33657033,"userid":33658417,"last_active_time":1698671439,"vacation":false,"place":"KOTA CIMAHI - CIMAHI UTARA, JAWA BARAT, ID","account":{"portrait":"ec1c81366363019aeeed49808703c94d","username":"bandung.topping","status":1},"is_shopee_verified":true,"is_preferred_plus_seller":true,"is_official_shop":false,"shop_location":"KOTA CIMAHI","item_count":752,"rating_star":4.828545,"response_rate":76,"session_info":null,"name":"Bandung Topping","ctime":1504760708,"response_time":6574,"follower_count":54549,"show_official_shop_label":false,"rating_bad":896,"rating_good":116631,"rating_normal":2586,"session_infos":null,"show_shopee_mission":false,"status":1,"is_individual_seller":null,"is_3pf":false}}