{"bff_meta":null,"error":null,"error_msg":null,"data":{"shopid":35535105,"userid":35536489,"last_active_time":1698671358,"vacation":false,"place":"KAB. TANGERANG - SEPATAN, BANTEN, ID","account":{"portrait":"5d6b1c4eddbc6415dc78d5a29098976c","username":"accesoriesmall","status":1},"is_shopee_verified":true,"is_preferred_plus_seller":true,"is_official_shop":false,"shop_location":"KAB. TANGERANG","item_count":1508,"rating_star":4.565621,"response_rate":95,"session_info":null,"name":"Mall Accesories","ctime":1505936149,"response_time":8087,"follower_count":28943,"show_official_shop_label":false,"rating_bad":4020,"rating_good":112898,"rating_normal":8916,"session_infos":null,"show_shopee_mission":false,"status":1,"is_individual_seller":null,"is_3pf":false}}