{"bff_meta":null,"error":null,"error_msg":null,"data":{"shopid":373204462,"userid":373224039,"last_active_time":1698671089,"vacation":false,"place":"KAB. BOGOR - CIAWI, JAWA BARAT, ID","account":{"portrait":"f50f2c79c745ad362893e0a111651b70","username":"eni_kaoskaki","status":1},"is_shopee_verified":true,"is_preferred_plus_seller":true,"is_official_shop":false,"shop_location":"KAB. BOGOR","item_count":210,"rating_star":4.770059,"response_rate":77,"session_info":null,"name":"Rubas_store","ctime":1610637243,"response_time":10004,"follower_count":26313,"show_official_shop_label":false,"rating_bad":481,"rating_good":68121,"rating_normal":2482,"session_infos":null,"show_shopee_mission":false,"status":1,"is_individual_seller":null,"is_3pf":false}}