{"bff_meta":null,"error":null,"error_msg":null,"data":{"shopid":39398138,"userid":39399524,"last_active_time":1698668666,"vacation":false,"place":"KOTA JAKARTA UTARA - TANJUNG PRIOK, DKI JAKARTA, ID","account":{"portrait":"b411e35c5ce0138dd43e25e5a99ff61f","username":"andrisanjaya_86","status":1},"is_shopee_verified":true,"is_preferred_plus_seller":true,"is_official_shop":false,"shop_location":"KOTA JAKARTA UTARA","item_count":303,"rating_star":4.866907,"response_rate":92,"session_info":null,"name":"SANJAYA ATK","ctime":1508397656,"response_time":5649,"follower_count":4365,"show_official_shop_label":false,"rating_bad":88,"rating_good":26462,"rating_normal":473,"session_infos":null,"show_shopee_mission":false,"status":1,"is_individual_seller":null,"is_3pf":false}}