{"bff_meta":null,"error":null,"error_msg":null,"data":{"shopid":413284604,"userid":413304181,"last_active_time":1698670699,"vacation":false,"place":"KOTA BEKASI - BEKASI UTARA, JAWA BARAT, ID","account":{"portrait":"3199a168a5834e9464534d69b74038e7","username":"arsitamastationery","status":1},"is_shopee_verified":true,"is_preferred_plus_seller":true,"is_official_shop":false,"shop_location":"KOTA BEKASI","item_count":1046,"rating_star":4.887098,"response_rate":99,"session_info":null,"name":"Arsitama Stationery","ctime":1617079481,"response_time":5088,"follower_count":7024,"show_official_shop_label":false,"rating_bad":50,"rating_good":12657,"rating_normal":175,"session_infos":null,"show_shopee_mission":false,"status":1,"is_individual_seller":null,"is_3pf":false}}