{"bff_meta":null,"error":null,"error_msg":null,"data":{"shopid":4139956,"userid":4141240,"last_active_time":1698671792,"vacation":false,"place":"KAB. PEKALONGAN - TIRTO, JAWA TENGAH, ID","account":{"portrait":"9f07bb0bb5b6d37b89ef2b00dd4f5ede","username":"hakiracollection","status":1},"is_shopee_verified":true,"is_preferred_plus_seller":true,"is_official_shop":false,"shop_location":"KAB. PEKALONGAN","item_count":79,"rating_star":4.743404,"response_rate":97,"session_info":null,"name":"hakiracollection","ctime":1458483220,"response_time":7203,"follower_count":57224,"show_official_shop_label":false,"rating_bad":303,"rating_good":31776,"rating_normal":1174,"session_infos":null,"show_shopee_mission":false,"status":1,"is_individual_seller":null,"is_3pf":false}}