{"bff_meta":null,"error":null,"error_msg":null,"data":{"shopid":41997829,"userid":41999215,"last_active_time":1698670983,"vacation":false,"place":"KAB. BANDUNG - RANCAEKEK, JAWA BARAT, ID","account":{"portrait":"ec482b639fcbf1f043849e6cf1a091c9","username":"jerry_shopbandung","status":1},"is_shopee_verified":false,"is_preferred_plus_seller":false,"is_official_shop":false,"shop_location":"KAB. BANDUNG","item_count":12,"rating_star":4.970779,"response_rate":97,"session_info":null,"name":"jerry_shopbandung","ctime":1510035473,"response_time":2115,"follower_count":1476,"show_official_shop_label":false,"rating_bad":5,"rating_good":17294,"rating_normal":34,"session_infos":null,"show_shopee_mission":false,"status":1,"is_individual_seller":null,"is_3pf":false}}