{"bff_meta":null,"error":null,"error_msg":null,"data":{"shopid":420548210,"userid":420567787,"last_active_time":1698660066,"vacation":false,"place":"KAB. LUMAJANG - LUMAJANG, JAWA TIMUR, ID","account":{"portrait":"17c9cc5a4b588b520f94b61c45107998","username":"bricejersey16","status":1},"is_shopee_verified":false,"is_preferred_plus_seller":false,"is_official_shop":false,"shop_location":"KAB. LUMAJANG","item_count":77,"rating_star":4.710744,"response_rate":46,"session_info":null,"name":"bricejersey16","ctime":1618039014,"response_time":9426,"follower_count":489,"show_official_shop_label":false,"rating_bad":6,"rating_good":350,"rating_normal":18,"session_infos":null,"show_shopee_mission":false,"status":1,"is_individual_seller":null,"is_3pf":false}}