{"bff_meta":null,"error":null,"error_msg":null,"data":{"shopid":42130099,"userid":42131485,"last_active_time":1698657391,"vacation":false,"place":"KAB. BATANG - BANDAR, JAWA TENGAH, ID","account":{"portrait":"f9aad0eee54fd53e722bc3ec031c68ca","username":"idasafitri123","status":1},"is_shopee_verified":true,"is_preferred_plus_seller":false,"is_official_shop":false,"shop_location":"KAB. BATANG","item_count":313,"rating_star":4.967442,"response_rate":86,"session_info":null,"name":"@baajuu_","ctime":1510111425,"response_time":8906,"follower_count":20883,"show_official_shop_label":false,"rating_bad":0,"rating_good":3955,"rating_normal":8,"session_infos":null,"show_shopee_mission":false,"status":1,"is_individual_seller":null,"is_3pf":false}}