{"bff_meta":null,"error":null,"error_msg":null,"data":{"shopid":43880270,"userid":43881656,"last_active_time":1698666410,"vacation":false,"place":"KOTA TANGERANG - KARANG TENGAH, BANTEN, ID","account":{"portrait":"976db7e59f73eba2b4e53eafeede35fb","username":"tigarasa","status":1},"is_shopee_verified":true,"is_preferred_plus_seller":false,"is_official_shop":false,"shop_location":"KOTA TANGERANG","item_count":202,"rating_star":4.942944,"response_rate":94,"session_info":null,"name":"tigarasa","ctime":1510923386,"response_time":1854,"follower_count":4699,"show_official_shop_label":false,"rating_bad":28,"rating_good":30717,"rating_normal":151,"session_infos":null,"show_shopee_mission":false,"status":1,"is_individual_seller":null,"is_3pf":false}}