{"bff_meta":null,"error":null,"error_msg":null,"data":{"shopid":4553317,"userid":4554607,"last_active_time":1698665840,"vacation":false,"place":"KOTA PARIAMAN - PARIAMAN SELATAN, SUMATERA BARAT, ID","account":{"portrait":"891b347594353b4c64fbd739765c19f7","username":"she777_","status":1},"is_shopee_verified":false,"is_preferred_plus_seller":false,"is_official_shop":false,"shop_location":"KOTA PARIAMAN","item_count":33,"rating_star":4.852533,"response_rate":21,"session_info":null,"name":"She777_","ctime":1460019014,"response_time":5298,"follower_count":12368,"show_official_shop_label":false,"rating_bad":23,"rating_good":3989,"rating_normal":72,"session_infos":null,"show_shopee_mission":false,"status":1,"is_individual_seller":null,"is_3pf":false}}