{"bff_meta":null,"error":null,"error_msg":null,"data":{"shopid":458239621,"userid":458259198,"last_active_time":1698672246,"vacation":false,"place":"KOTA SURABAYA - SUKOLILO, JAWA TIMUR, ID","account":{"portrait":"28237a2d81a5bd739c1e375b482c4f28","username":"surgaboyz","status":1},"is_shopee_verified":true,"is_preferred_plus_seller":true,"is_official_shop":false,"shop_location":"KOTA SURABAYA","item_count":7463,"rating_star":4.790214,"response_rate":100,"session_info":null,"name":"SURGABOYZ2020","ctime":1622740206,"response_time":1198,"follower_count":7539,"show_official_shop_label":false,"rating_bad":1250,"rating_good":106417,"rating_normal":3021,"session_infos":null,"show_shopee_mission":false,"status":1,"is_individual_seller":null,"is_3pf":false}}