{"bff_meta":null,"error":null,"error_msg":null,"data":{"shopid":49452874,"userid":49454262,"last_active_time":1698669661,"vacation":false,"place":"KAB. BANDUNG - KATAPANG, JAWA BARAT, ID","account":{"portrait":"2f7f774ccac84f431a672b15a0919872","username":"razena.store","status":1},"is_shopee_verified":true,"is_preferred_plus_seller":true,"is_official_shop":false,"shop_location":"KAB. BANDUNG","item_count":343,"rating_star":4.829036,"response_rate":93,"session_info":null,"name":"RAZENA STORE","ctime":1514048764,"response_time":6278,"follower_count":12325,"show_official_shop_label":false,"rating_bad":99,"rating_good":13337,"rating_normal":301,"session_infos":null,"show_shopee_mission":false,"status":1,"is_individual_seller":null,"is_3pf":false}}