{"bff_meta":null,"error":null,"error_msg":null,"data":{"shopid":52133300,"userid":52134688,"last_active_time":1698672114,"vacation":false,"place":"KAB. BEKASI - TAMBUN SELATAN, JAWA BARAT, ID","account":{"portrait":"94e16365348dcedc97b82a516c550a27","username":"mainanmurahjkt","status":1},"is_shopee_verified":true,"is_preferred_plus_seller":true,"is_official_shop":false,"shop_location":"KAB. BEKASI","item_count":1365,"rating_star":4.74181,"response_rate":99,"session_info":{"is_show":true,"session_id":45240652,"view_count":12,"session_url":"https://play-tx-src.livestream.shopee.co.id/live/id-live-7550-45240652.flv?auditkey=1.0~TT77bSwyxhlxTlozLOV-jbUrCDW-YBbJVOVhXtUBL3KWgk_64zEugujsMkyTM5tvc_frvU4oGtj8JB0gqGBd0kSqTaDWa6Ym5vyI-WcGY4s~edec376c016171b57329fa0ef1394519d17e7af0b755990620c7166d5479396c\u0026cdnID=TXCLOUD\u0026expire_ts=1698673934","preview_image":"id-11134104-7r98z-lmy1589pvzqsd7"},"name":"mainanmurahjkt","ctime":1515765853,"response_time":8230,"follower_count":456199,"show_official_shop_label":false,"rating_bad":5197,"rating_good":546878,"rating_normal":24325,"session_infos":[{"is_show":true,"session_id":45240652,"view_count":12,"session_url":"https://play-tx-src.livestream.shopee.co.id/live/id-live-7550-45240652.flv?auditkey=1.0~TT77bSwyxhlxTlozLOV-jbUrCDW-YBbJVOVhXtUBL3KWgk_64zEugujsMkyTM5tvc_frvU4oGtj8JB0gqGBd0kSqTaDWa6Ym5vyI-WcGY4s~edec376c016171b57329fa0ef1394519d17e7af0b755990620c7166d5479396c\u0026cdnID=TXCLOUD\u0026expire_ts=1698673934","preview_image":"id-11134104-7r98z-lmy1589pvzqsd7"}],"show_shopee_mission":false,"status":1,"is_individual_seller":null,"is_3pf":false}}