{"bff_meta":null,"error":null,"error_msg":null,"data":{"shopid":5379485,"userid":5380779,"last_active_time":1698671009,"vacation":false,"place":"KOTA BANDUNG - BATUNUNGGAL, JAWA BARAT, ID","account":{"portrait":"98f9cb38f2fb5bfe51b1eb269b7fde16","username":"sweaterwanita.id","status":1},"is_shopee_verified":true,"is_preferred_plus_seller":true,"is_official_shop":false,"shop_location":"KOTA BANDUNG","item_count":56,"rating_star":4.68607,"response_rate":82,"session_info":{"is_show":true,"session_id":45248484,"view_count":3,"session_url":"https://play-ws-src.livestream.shopee.co.id/livestreaming/id-live-14603-45248484.flv?auditkey=1.0~3r1MckNROLOl474oSGYhADj5LtbhBbwmZfDzdH-7dyM0k7kcNMoHzhaDN2V0hm3lIrTj9CuKjQvSmTQ5Nc4O1A~5ea27d000d7c187cee99aeabd0162f23fa3bf425601cd126306a29502db1a416\u0026cdnID=WANGSU\u0026expire_ts=1698672966","preview_image":"id-11134104-7r98x-lngqa0cz9k6349"},"name":"SWEATER WANITA ","ctime":1462455450,"response_time":7536,"follower_count":53745,"show_official_shop_label":false,"rating_bad":636,"rating_good":63688,"rating_normal":3053,"session_infos":[{"is_show":true,"session_id":45248484,"view_count":3,"session_url":"https://play-ws-src.livestream.shopee.co.id/livestreaming/id-live-14603-45248484.flv?auditkey=1.0~3r1MckNROLOl474oSGYhADj5LtbhBbwmZfDzdH-7dyM0k7kcNMoHzhaDN2V0hm3lIrTj9CuKjQvSmTQ5Nc4O1A~5ea27d000d7c187cee99aeabd0162f23fa3bf425601cd126306a29502db1a416\u0026cdnID=WANGSU\u0026expire_ts=1698672966","preview_image":"id-11134104-7r98x-lngqa0cz9k6349"}],"show_shopee_mission":false,"status":1,"is_individual_seller":null,"is_3pf":false}}