{"bff_meta":null,"error":null,"error_msg":null,"data":{"shopid":54221744,"userid":54223168,"last_active_time":1698665609,"vacation":false,"place":"KOTA MALANG - KEDUNGKANDANG, JAWA TIMUR, ID","account":{"portrait":"63ac2fd34c7c7b5dd9a806af16598c9b","username":"mylo_shoecleaner","status":1},"is_shopee_verified":false,"is_preferred_plus_seller":false,"is_official_shop":false,"shop_location":"KOTA MALANG","item_count":57,"rating_star":4.742909,"response_rate":73,"session_info":null,"name":"mylo_shoecleaner","ctime":1517063983,"response_time":4050,"follower_count":607,"show_official_shop_label":false,"rating_bad":7,"rating_good":1047,"rating_normal":43,"session_infos":null,"show_shopee_mission":false,"status":1,"is_individual_seller":null,"is_3pf":false}}