{"bff_meta":null,"error":null,"error_msg":null,"data":{"shopid":54341780,"userid":54343205,"last_active_time":1698665888,"vacation":false,"place":"KOTA JAKARTA BARAT - TAMBORA, DKI JAKARTA, ID","account":{"portrait":"a26e5d2b1c0d8bb8d04f86131b0f5119","username":"galuben","status":1},"is_shopee_verified":true,"is_preferred_plus_seller":true,"is_official_shop":false,"shop_location":"KOTA JAKARTA BARAT","item_count":195,"rating_star":4.773273,"response_rate":98,"session_info":null,"name":"Galuben","ctime":1517142809,"response_time":4236,"follower_count":24514,"show_official_shop_label":false,"rating_bad":1548,"rating_good":129336,"rating_normal":4529,"session_infos":null,"show_shopee_mission":false,"status":1,"is_individual_seller":null,"is_3pf":false}}