{"bff_meta":null,"error":null,"error_msg":null,"data":{"shopid":54362879,"userid":54364303,"last_active_time":1698672025,"vacation":false,"place":"KOTA BEKASI - PONDOK MELATI, JAWA BARAT, ID","account":{"portrait":"9936fecde97cbe4496e40777c8f5c31c","username":"charme.id","status":1},"is_shopee_verified":true,"is_preferred_plus_seller":true,"is_official_shop":false,"shop_location":"KOTA BEKASI","item_count":2358,"rating_star":4.857695,"response_rate":91,"session_info":{"is_show":true,"session_id":45248107,"view_count":10,"session_url":"https://play-tx-src.livestream.shopee.co.id/live/id-live-12783-45248107.flv?auditkey=1.0~j7lU2wAmNFc3tGgvXJD_6HUo2Nkkvg9gbSfzb_7M7CI4LOQumSS3Vxpmi40lCFoQdba8JfhVhj9D9RU6YU-VO248aVZhKfegCzF4tUYctqc~14a9b6907a64a3db8cf511aedb86058f426c345f47467fe820037646052fd8ab\u0026cdnID=TXCLOUD\u0026expire_ts=1698673839","preview_image":"id-11134104-7r98v-lnh7i0q83ypzf1"},"name":"Charme Official Store","ctime":1517150511,"response_time":12546,"follower_count":162364,"show_official_shop_label":false,"rating_bad":938,"rating_good":198923,"rating_normal":3682,"session_infos":[{"is_show":true,"session_id":45248107,"view_count":10,"session_url":"https://play-tx-src.livestream.shopee.co.id/live/id-live-12783-45248107.flv?auditkey=1.0~j7lU2wAmNFc3tGgvXJD_6HUo2Nkkvg9gbSfzb_7M7CI4LOQumSS3Vxpmi40lCFoQdba8JfhVhj9D9RU6YU-VO248aVZhKfegCzF4tUYctqc~14a9b6907a64a3db8cf511aedb86058f426c345f47467fe820037646052fd8ab\u0026cdnID=TXCLOUD\u0026expire_ts=1698673839","preview_image":"id-11134104-7r98v-lnh7i0q83ypzf1"}],"show_shopee_mission":false,"status":1,"is_individual_seller":null,"is_3pf":false}}