{"bff_meta":null,"error":null,"error_msg":null,"data":{"shopid":55284998,"userid":55286422,"last_active_time":1698671426,"vacation":false,"place":"KOTA JAKARTA BARAT - TAMAN SARI, DKI JAKARTA, ID","account":{"portrait":"b977e71e6c04b0e373b36e970ff7cf31","username":"aseanshop123","status":1},"is_shopee_verified":true,"is_preferred_plus_seller":true,"is_official_shop":false,"shop_location":"KOTA JAKARTA BARAT","item_count":159,"rating_star":4.911802,"response_rate":93,"session_info":null,"name":"aseanshop123","ctime":1517683373,"response_time":7260,"follower_count":11286,"show_official_shop_label":false,"rating_bad":59,"rating_good":29803,"rating_normal":309,"session_infos":null,"show_shopee_mission":false,"status":1,"is_individual_seller":null,"is_3pf":false}}