{"bff_meta":null,"error":null,"error_msg":null,"data":{"shopid":5750838,"userid":5752137,"last_active_time":1698668197,"vacation":false,"place":"KAB. TANGERANG - KELAPA DUA, BANTEN, ID","account":{"portrait":"e5df27b77b3d57c44531442c31aed577","username":"sopianhadi_accessories1981.","status":1},"is_shopee_verified":true,"is_preferred_plus_seller":true,"is_official_shop":false,"shop_location":"KAB. TANGERANG","item_count":490,"rating_star":4.72552,"response_rate":92,"session_info":null,"name":"Sopianhadi_accessories1981","ctime":1463456545,"response_time":8132,"follower_count":5044,"show_official_shop_label":false,"rating_bad":205,"rating_good":11594,"rating_normal":470,"session_infos":null,"show_shopee_mission":false,"status":1,"is_individual_seller":null,"is_3pf":false}}