{"bff_meta":null,"error":null,"error_msg":null,"data":{"shopid":58834381,"userid":58835811,"last_active_time":1698670902,"vacation":false,"place":"KOTA JAKARTA PUSAT - CEMPAKA PUTIH, DKI JAKARTA, ID","account":{"portrait":"50d06aea267cfbc179ffaf584c7607a4","username":"toko.anugerah","status":1},"is_shopee_verified":true,"is_preferred_plus_seller":true,"is_official_shop":false,"shop_location":"KOTA JAKARTA PUSAT","item_count":756,"rating_star":4.948038,"response_rate":99,"session_info":{"is_show":true,"session_id":45248042,"view_count":6,"session_url":"https://play-hw-src.livestream.shopee.co.id/live/id-live-10056-45248042.flv?auditkey=1.0~XTE5DR-8FUN-UIHRMYHFcx6dWE-lZ5a-uBkuFTs8b_GAZuvV2pgzeZD9-pIYRixhBKxI8mBbjq5v9qAzg_XxqzaD7G6PVgGw6EhCzCJrIRg~2149470e9578c983d35bb912652a9713a400720fd746daa65d86180b97ec8444\u0026cdnID=HUAWEI\u0026expire_ts=1698673101","preview_image":"id-11134104-7qukx-lk9b4qd73pre4a"},"name":"Toko.Anugerah","ctime":1519970002,"response_time":4401,"follower_count":6242,"show_official_shop_label":false,"rating_bad":49,"rating_good":59365,"rating_normal":201,"session_infos":[{"is_show":true,"session_id":45248042,"view_count":6,"session_url":"https://play-hw-src.livestream.shopee.co.id/live/id-live-10056-45248042.flv?auditkey=1.0~XTE5DR-8FUN-UIHRMYHFcx6dWE-lZ5a-uBkuFTs8b_GAZuvV2pgzeZD9-pIYRixhBKxI8mBbjq5v9qAzg_XxqzaD7G6PVgGw6EhCzCJrIRg~2149470e9578c983d35bb912652a9713a400720fd746daa65d86180b97ec8444\u0026cdnID=HUAWEI\u0026expire_ts=1698673101","preview_image":"id-11134104-7qukx-lk9b4qd73pre4a"}],"show_shopee_mission":false,"status":1,"is_individual_seller":null,"is_3pf":false}}