{"bff_meta":null,"error":null,"error_msg":null,"data":{"shopid":59510213,"userid":59511643,"last_active_time":1698671847,"vacation":false,"place":"KOTA JAKARTA BARAT - CENGKARENG, DKI JAKARTA, ID","account":{"portrait":"1680fe775fa44043a4a3cad7122cb7b9","username":"mayoraofficialstore","status":1},"is_shopee_verified":false,"is_preferred_plus_seller":false,"is_official_shop":true,"shop_location":"KOTA JAKARTA BARAT","item_count":271,"rating_star":4.870837,"response_rate":99,"session_info":null,"name":"Mayora Official Shop","ctime":1520346771,"response_time":6844,"follower_count":190064,"show_official_shop_label":true,"rating_bad":2332,"rating_good":346749,"rating_normal":6134,"session_infos":null,"show_shopee_mission":false,"status":1,"is_individual_seller":null,"is_3pf":false}}