{"bff_meta":null,"error":null,"error_msg":null,"data":{"shopid":59878741,"userid":59880175,"last_active_time":1698671525,"vacation":false,"place":"KOTA SURABAYA - KARANGPILANG, JAWA TIMUR, ID","account":{"portrait":"2f666e48878a0e1e42ff4d57f3694b3a","username":"gain_officialstore","status":1},"is_shopee_verified":true,"is_preferred_plus_seller":true,"is_official_shop":false,"shop_location":"KOTA SURABAYA","item_count":93,"rating_star":4.840608,"response_rate":80,"session_info":null,"name":"Gain Official Store","ctime":1520577797,"response_time":11466,"follower_count":810,"show_official_shop_label":false,"rating_bad":28,"rating_good":3656,"rating_normal":77,"session_infos":null,"show_shopee_mission":false,"status":1,"is_individual_seller":null,"is_3pf":false}}