{"bff_meta":null,"error":null,"error_msg":null,"data":{"shopid":6510187,"userid":6511500,"last_active_time":1698669992,"vacation":false,"place":"KOTA BANDUNG - CICENDO, JAWA BARAT, ID","account":{"portrait":"80c34eaed227ba4efeb5967ff0ed4e67","username":"depotkarunia","status":1},"is_shopee_verified":true,"is_preferred_plus_seller":true,"is_official_shop":false,"shop_location":"KOTA BANDUNG","item_count":381,"rating_star":4.842891,"response_rate":99,"session_info":null,"name":"Depot Karunia","ctime":1465242300,"response_time":2537,"follower_count":14263,"show_official_shop_label":false,"rating_bad":78,"rating_good":19453,"rating_normal":395,"session_infos":null,"show_shopee_mission":false,"status":1,"is_individual_seller":null,"is_3pf":false}}