{"bff_meta":null,"error":null,"error_msg":null,"data":{"shopid":6597360,"userid":6598674,"last_active_time":1698672285,"vacation":false,"place":"KAB. BANDUNG - MARGAHAYU, JAWA BARAT, ID","account":{"portrait":"76a48ba5499c5a86c22f6f97f082ece5","username":"kingshoes.pm","status":1},"is_shopee_verified":true,"is_preferred_plus_seller":true,"is_official_shop":false,"shop_location":"KAB. BANDUNG","item_count":220,"rating_star":4.805564,"response_rate":98,"session_info":null,"name":"Kingshoes.Pm","ctime":1465436637,"response_time":1408,"follower_count":3945,"show_official_shop_label":false,"rating_bad":34,"rating_good":6197,"rating_normal":171,"session_infos":null,"show_shopee_mission":false,"status":1,"is_individual_seller":null,"is_3pf":false}}