{"bff_meta":null,"error":null,"error_msg":null,"data":{"shopid":69061319,"userid":69062777,"last_active_time":1698671472,"vacation":false,"place":"KOTA JAKARTA PUSAT - KEMAYORAN, DKI JAKARTA, ID","account":{"portrait":"id-11134216-7qul1-ljl1bwqw4von26","username":"auto_bdo_berkat_doa_orangtua","status":1},"is_shopee_verified":true,"is_preferred_plus_seller":false,"is_official_shop":false,"shop_location":"KOTA JAKARTA PUSAT","item_count":1020,"rating_star":4.759283,"response_rate":91,"session_info":null,"name":"Auto_BDO_Berkat_Doa_Orangtua","ctime":1526041657,"response_time":8574,"follower_count":11334,"show_official_shop_label":false,"rating_bad":1241,"rating_good":106854,"rating_normal":3815,"session_infos":null,"show_shopee_mission":false,"status":1,"is_individual_seller":null,"is_3pf":false}}