{"bff_meta":null,"error":null,"error_msg":null,"data":{"shopid":73082841,"userid":73084304,"last_active_time":1698667866,"vacation":false,"place":"KOTA JAKARTA BARAT - CENGKARENG, DKI JAKARTA, ID","account":{"portrait":"e35a260cf0e5400e537010f70deb9d16","username":"cecilia_f1","status":1},"is_shopee_verified":true,"is_preferred_plus_seller":false,"is_official_shop":false,"shop_location":"KOTA JAKARTA BARAT","item_count":595,"rating_star":4.775169,"response_rate":26,"session_info":null,"name":"cecilia_f1","ctime":1528097588,"response_time":11115,"follower_count":4332,"show_official_shop_label":false,"rating_bad":372,"rating_good":35236,"rating_normal":1233,"session_infos":null,"show_shopee_mission":false,"status":1,"is_individual_seller":null,"is_3pf":false}}