{"bff_meta":null,"error":null,"error_msg":null,"data":{"shopid":75469990,"userid":75471460,"last_active_time":1698669584,"vacation":false,"place":"KOTA SURABAYA - KARANGPILANG, JAWA TIMUR, ID","account":{"portrait":"fe554dfff738dbb6da8c41cdb74868d0","username":"anfalaan","status":1},"is_shopee_verified":true,"is_preferred_plus_seller":true,"is_official_shop":false,"shop_location":"KOTA SURABAYA","item_count":112,"rating_star":4.842549,"response_rate":94,"session_info":null,"name":"anfalaan","ctime":1529485118,"response_time":2796,"follower_count":948,"show_official_shop_label":false,"rating_bad":21,"rating_good":5672,"rating_normal":109,"session_infos":null,"show_shopee_mission":false,"status":1,"is_individual_seller":null,"is_3pf":false}}