{"bff_meta":null,"error":null,"error_msg":null,"data":{"shopid":78556176,"userid":78557651,"last_active_time":1698671458,"vacation":false,"place":"KOTA JAKARTA BARAT - GROGOL PETAMBURAN, DKI JAKARTA, ID","account":{"portrait":"7277b1d4577c8a7bfa830ef94f765018","username":"flymanofficial","status":1},"is_shopee_verified":false,"is_preferred_plus_seller":false,"is_official_shop":true,"shop_location":"KOTA JAKARTA BARAT","item_count":51,"rating_star":4.864042,"response_rate":100,"session_info":null,"name":"Flyman Official Shop","ctime":1531213616,"response_time":436,"follower_count":86275,"show_official_shop_label":true,"rating_bad":420,"rating_good":148330,"rating_normal":2414,"session_infos":null,"show_shopee_mission":false,"status":1,"is_individual_seller":null,"is_3pf":false}}