{"bff_meta":null,"error":null,"error_msg":null,"data":{"shopid":79113290,"userid":79114765,"last_active_time":1698672013,"vacation":false,"place":"KOTA DEPOK - CIPAYUNG, JAWA BARAT, ID","account":{"portrait":"3ab6eacd381ec8b35fb3d47836023d8e","username":"markaskulakan","status":1},"is_shopee_verified":true,"is_preferred_plus_seller":false,"is_official_shop":false,"shop_location":"KOTA DEPOK","item_count":62,"rating_star":4.76492,"response_rate":60,"session_info":null,"name":"Rynstelle Legging","ctime":1531493193,"response_time":10224,"follower_count":48387,"show_official_shop_label":false,"rating_bad":272,"rating_good":78860,"rating_normal":2731,"session_infos":null,"show_shopee_mission":false,"status":1,"is_individual_seller":null,"is_3pf":false}}