{"bff_meta":null,"error":null,"error_msg":null,"data":{"shopid":8155571,"userid":8156867,"last_active_time":1698671650,"vacation":false,"place":"KOTA JAKARTA BARAT - TAMBORA, DKI JAKARTA, ID","account":{"portrait":"3deb6ec86aaedea6a356249dcd7d384e","username":"aureendarmali","status":1},"is_shopee_verified":true,"is_preferred_plus_seller":true,"is_official_shop":false,"shop_location":"KOTA JAKARTA BARAT","item_count":123,"rating_star":4.667559,"response_rate":84,"session_info":{"is_show":true,"session_id":45255833,"view_count":35,"session_url":"https://play-tx-src.livestream.shopee.co.id/live/id-live-45818-45255833_spehqld.flv?auditkey=1.0~7-q4yn2jNPlsqSOO66XXrLOicGhUzg-oHKkdptckkLKmxgHOk4NyBKg8zBKjq7e-sRHf4-sIeLX5SdOobX112Q~49f976b0460e0ab896addce36e2a031d24383eb0e91117ca0d7ec551ba636266\u0026cdnID=TXCLOUD\u0026expire_ts=1698673490","preview_image":"id-11134104-7r992-lmofhwrcdxn0da"},"name":"Subur Berkat Furniture","ctime":1469261330,"response_time":8336,"follower_count":48427,"show_official_shop_label":false,"rating_bad":1032,"rating_good":67843,"rating_normal":4156,"session_infos":[{"is_show":true,"session_id":45255833,"view_count":35,"session_url":"https://play-tx-src.livestream.shopee.co.id/live/id-live-45818-45255833_spehqld.flv?auditkey=1.0~7-q4yn2jNPlsqSOO66XXrLOicGhUzg-oHKkdptckkLKmxgHOk4NyBKg8zBKjq7e-sRHf4-sIeLX5SdOobX112Q~49f976b0460e0ab896addce36e2a031d24383eb0e91117ca0d7ec551ba636266\u0026cdnID=TXCLOUD\u0026expire_ts=1698673490","preview_image":"id-11134104-7r992-lmofhwrcdxn0da"}],"show_shopee_mission":false,"status":1,"is_individual_seller":null,"is_3pf":false}}