{"bff_meta":null,"error":null,"error_msg":null,"data":{"shopid":8655454,"userid":8656750,"last_active_time":1698669237,"vacation":false,"place":"KAB. BANTUL - BANGUNTAPAN, DI YOGYAKARTA, ID","account":{"portrait":"cd5e7c2bea42310cb49e1419a8a4d7b9","username":"kikimanyu","status":1},"is_shopee_verified":false,"is_preferred_plus_seller":false,"is_official_shop":false,"shop_location":"KAB. BANTUL","item_count":39,"rating_star":4.684292,"response_rate":90,"session_info":null,"name":"kikimanyu","ctime":1470499928,"response_time":5412,"follower_count":1533,"show_official_shop_label":false,"rating_bad":5,"rating_good":632,"rating_normal":34,"session_infos":null,"show_shopee_mission":false,"status":1,"is_individual_seller":null,"is_3pf":false}}