{"bff_meta":null,"error":null,"error_msg":null,"data":{"shopid":8900396,"userid":8901692,"last_active_time":1698669687,"vacation":false,"place":"KOTA JAKARTA PUSAT - KEMAYORAN, DKI JAKARTA, ID","account":{"portrait":"f2d7f3874c4505970e9ab105e4cec93d","username":"ladylikes","status":1},"is_shopee_verified":true,"is_preferred_plus_seller":true,"is_official_shop":false,"shop_location":"KOTA JAKARTA PUSAT","item_count":375,"rating_star":4.877399,"response_rate":90,"session_info":null,"name":"Ladylikes","ctime":1471154284,"response_time":6359,"follower_count":24783,"show_official_shop_label":false,"rating_bad":282,"rating_good":143791,"rating_normal":1977,"session_infos":null,"show_shopee_mission":false,"status":1,"is_individual_seller":null,"is_3pf":false}}