{"bff_meta":null,"error":null,"error_msg":null,"data":{"shopid":95487657,"userid":95489135,"last_active_time":1698671738,"vacation":false,"place":"KOTA JAKARTA UTARA - TANJUNG PRIOK, DKI JAKARTA, ID","account":{"portrait":"77ef5a733e93b9fdee059385b092cbb8","username":"gilogilo","status":1},"is_shopee_verified":true,"is_preferred_plus_seller":true,"is_official_shop":false,"shop_location":"KOTA JAKARTA UTARA","item_count":479,"rating_star":4.792822,"response_rate":100,"session_info":null,"name":"gilogilo","ctime":1539146458,"response_time":4055,"follower_count":38537,"show_official_shop_label":false,"rating_bad":749,"rating_good":88594,"rating_normal":2687,"session_infos":null,"show_shopee_mission":false,"status":1,"is_individual_seller":null,"is_3pf":false}}