{"bff_meta":null,"error":null,"error_msg":null,"data":{"shopid":9952343,"userid":9953640,"last_active_time":1698660649,"vacation":false,"place":"KAB. SRAGEN - SRAGEN, JAWA TENGAH, ID","account":{"portrait":"4e405ab1762b140ffcc05a3d3c7d5e26","username":"sumberagung","status":1},"is_shopee_verified":true,"is_preferred_plus_seller":true,"is_official_shop":false,"shop_location":"KAB. SRAGEN","item_count":3492,"rating_star":4.569929,"response_rate":84,"session_info":null,"name":"Sumber Agung","ctime":1473848530,"response_time":11730,"follower_count":11119,"show_official_shop_label":false,"rating_bad":3165,"rating_good":90936,"rating_normal":6611,"session_infos":null,"show_shopee_mission":false,"status":1,"is_individual_seller":null,"is_3pf":false}}